shyster/__init__.py
shyster/_modidx.py
shyster/file.py
shyster/html.py
shyster/hyphenation.py
shyster/main.py
shyster/pattern.py
shyster-0.0.3.dist-info/LICENSE
shyster-0.0.3.dist-info/METADATA
shyster-0.0.3.dist-info/WHEEL
shyster-0.0.3.dist-info/entry_points.txt
shyster-0.0.3.dist-info/top_level.txt
shyster-0.0.3.dist-info/RECORD
