Metadata-Version: 2.1
Name: shyster
Version: 0.0.3
Summary: Add soft hyphens to HTML documents
Home-page: https://github.com/jkseppan/shyster
Author: Jouni K. Seppänen
Author-email: jks@iki.fi
License: GNU General Public License v3
Keywords: hyphenation shy tex
Platform: UNKNOWN
Classifier: Development Status :: 4 - Beta
Classifier: Intended Audience :: Developers
Classifier: Natural Language :: English
Classifier: Programming Language :: Python :: 3.10
Classifier: License :: OSI Approved :: GNU General Public License v3 (GPLv3)
Requires-Python: >=3.10
License-File: LICENSE
Requires-Dist: bs4
Requires-Dist: lxml
Requires-Dist: datrie (>=0.8.2)
Provides-Extra: dev
Requires-Dist: types-beautifulsoup4 ; extra == 'dev'
Requires-Dist: requests ; extra == 'dev'
